README.md
setup.py
avalontm_libs/console.py
avalontm_libs/mysql.py
avalontm_libs.egg-info/PKG-INFO
avalontm_libs.egg-info/SOURCES.txt
avalontm_libs.egg-info/dependency_links.txt
avalontm_libs.egg-info/requires.txt
avalontm_libs.egg-info/top_level.txt