Metadata-Version: 2.1
Name: avalontm-libs
Version: 0.2
Summary: Libreria simple para usarlo en python
Home-page: https://github.com/avalontm/avalonmt_libs
Download-URL: https://github.com/avalontm/avalonmt_libs/tarball/0.2
Author: AvalonTM
Author-email: 
License: MIT
Keywords: mysql,database,data base
